LICENSE
MANIFEST.in
Makefile
README.rst
setup.py
irwin/__init__.py
irwin/__main__.py
irwin/canvas.py
irwin/plot.py
irwin/timeseries.py
irwin/version.py
irwin.egg-info/PKG-INFO
irwin.egg-info/SOURCES.txt
irwin.egg-info/dependency_links.txt
irwin.egg-info/entry_points.txt
irwin.egg-info/top_level.txt
irwin/subparsers/__init__.py
irwin/subparsers/plot.py
irwin/subparsers/watch.py
tests/__init__.py
tests/test_canvas.py