Metadata-Version: 1.1
Name: irwin
Version: 0.11.0
Summary:  Plotting data in the terminal.
Home-page: https://github.com/eerimoq/irwin
Author: Erik Moqvist
Author-email: erik.moqvist@gmail.com
License: MIT
Keywords: plot,terminal,canvas
Platform: UNKNOWN
Classifier: License :: OSI Approved :: MIT License
Classifier: Programming Language :: Python :: 3
